interface_proxy/__init__.py
interface_proxy/client.py
interface_proxy/py.typed
interface_proxy/server.py
interface_proxy-0.2.1b0.dist-info/LICENSE.txt
interface_proxy-0.2.1b0.dist-info/METADATA
interface_proxy-0.2.1b0.dist-info/WHEEL
interface_proxy-0.2.1b0.dist-info/top_level.txt
interface_proxy-0.2.1b0.dist-info/RECORD
