Metadata-Version: 2.1
Name: interface-proxy
Version: 0.2.1b0
Summary: A library that allows to import a module in one process (server) and use that module in another process (client).
Maintainer-email: SweepMe! GmbH <contact@sweep-me.net>
License: MIT License
Project-URL: Repository, https://github.com/SweepMe/interface-proxy
Classifier: Programming Language :: Python :: 3
Classifier: License :: OSI Approved :: MIT License
Classifier: Operating System :: Microsoft :: Windows
Classifier: Intended Audience :: Developers
Classifier: Topic :: Software Development :: Libraries :: Python Modules
Requires-Python: >=3.8
License-File: LICENSE.txt
Requires-Dist: tblib ~=2.0.0
Requires-Dist: pywin32 ==306
Requires-Dist: six ~=1.16.0
Provides-Extra: dev
Requires-Dist: tox ~=4.12.1 ; extra == 'dev'
Requires-Dist: ruff ~=0.2.1 ; extra == 'dev'
Requires-Dist: black ~=24.1.1 ; extra == 'dev'
Requires-Dist: mypy ~=1.8.0 ; extra == 'dev'
Requires-Dist: pytest ~=8.0.0 ; extra == 'dev'
Provides-Extra: typed
Requires-Dist: types-six ~=1.16.21 ; extra == 'typed'
Requires-Dist: types-pywin32 ~=306.0.0 ; extra == 'typed'
